tindicators/__init__.py
tindicators/impl.py
tindicators/indicators.dll
tindicators/libindicators.dylib
tindicators/libindicators.so
tindicators/test_.py
tindicators-0.9.12.dist-info/METADATA
tindicators-0.9.12.dist-info/WHEEL
tindicators-0.9.12.dist-info/top_level.txt
tindicators-0.9.12.dist-info/RECORD
